{ "_id" : { "$oid" : "50f82aeab4aa879861000000" }, "text" : "Golden Globes, lots of fashion messes...but glad Argo won. Really good movie, along w Moonrise Kingdom and Salmon Fishing Yeman.", "created_at" : { "$date" : 1358137508000 }, "id" : 290675893024747523, "user" : { "screen_name" : "Dpharmakis23", "id" : 852045842 } }
{ "_id" : { "$oid" : "50f82aeab4aa879861000001" }, "text" : "RT @RPLife: 2 Red Carpet HQs added and maybe my favorites of the night http://t.co/Fiq08m7i", "created_at" : { "$date" : 1358137507000 }, "id" : 290675892668211203, "user" : { "screen_name" : "dri_violet", "id" : 88925839 } }
{ "_id" : { "$oid" : "50f82aeab4aa879861000002" }, "text" : "After watching the Golden Globes it made me want to watch Les Mis again. It's gonna be a late night tonight.", "created_at" : { "$date" : 1358137507000 }, "id" : 290675892416573440, "user" : { "screen_name" : "JessBess4", "id" : 273137370 } }
{ "_id" : { "$oid" : "50f82aeab4aa879861000003" }, "text" : "I'm pretty how I've felt during the Golden Globes is how most of my followers feel during a NASCAR race/football game. #TweetOverload", "created_at" : { "$date" : 1358137507000 }, "id" : 290675892311715840, "user" : { "screen_name" : "JordanTMcGraw", "id" : 25172777 } }
{ "_id" : { "$oid" : "50f82aeab4aa879861000004" }, "text" : "RT @LaAbuela961: Hay personas que solo compran ropa en Jacarandas pero se pasaron criticando los vestuarios de los famosos en los Golden Globes. #NoMeJodan", "created_at" : { "$date" : 1358137507000 }, "id" : 290675892278157313, "user" : { "screen_name" : "silvita_hdez", "id" : 269487031 } }
{ "_id" : { "$oid" : "50f82aeab4aa879861000005" }, "text" : "No puedo creer que ya hayan gifs de los Golden Globes, permiso me voy a Tumblr.", "created_at" : { "$date" : 1358137507000 }, "id" : 290675892240412672, "user" : { "screen_name" : "JennyPadawan", "id" : 101654642 } }
{ "_id" : { "$oid" : "50f82aeab4aa879861000006" }, "text" : "My fave dresses at Golden Globes 👗 #fashion #amyadams #meganfox #rosiehw #cantsleep http://t.co/ZFMALMkA", "created_at" : { "$date" : 1358137507000 }, "id" : 290675892227817473, "user" : { "screen_name" : "Gill27031", "id" : 22059724 } }
{ "_id" : { "$oid" : "50f82aeab4aa879861000007" }, "text" : "\"Kristen Stewart Makes Surprise Appearance At 2013 Golden Globes\" OI???????????", "created_at" : { "$date" : 1358137507000 }, "id" : 290675892194267136, "user" : { "screen_name" : "maricheq", "id" : 29998743 } }
{ "_id" : { "$oid" : "50f82aeab4aa879861000008" }, "text" : "Jessica Chastain, Best Actress Drama Winner At Golden Globes 2013 http://t.co/MmUc3iPJ", "created_at" : { "$date" : 1358137507000 }, "id" : 290675892177477632, "user" : { "screen_name" : "NehaThakur27", "id" : 464439857 } }
{ "_id" : { "$oid" : "50f82aeab4aa879861000009" }, "text" : "😱👏 Golden Globes 2013 http://t.co/2y6kNxwn vía @glamourmaguk", "created_at" : { "$date" : 1358137507000 }, "id" : 290675891955187713, "user" : { "screen_name" : "isafloresp", "id" : 131027218 } }
{ "_id" : { "$oid" : "50f82aeab4aa87986100000a" }, "text" : "Jennifer Lawrence vs. Zooey Deschanel: It's the Golden Globes Red Carpet Pose-Off!: It's a lady in red showdown! Jennifer Lawrence an...", "created_at" : { "$date" : 1358137507000 }, "id" : 290675891544150016, "user" : { "screen_name" : "taylor_debery", "id" : 1029586123 } }